arxivai/__init__.py
arxivai/api.py
arxivai/embedding.py
arxivai/main.py
arxivai/pdf.py
arxivai-0.0.36.dist-info/METADATA
arxivai-0.0.36.dist-info/WHEEL
arxivai-0.0.36.dist-info/RECORD
