Metadata-Version: 2.1
Name: arxivai
Version: 0.0.36
Summary: Utilities for arXiv AI - https://arxivai.org/
Author: Bongsang Kim
Author-email: happykbs@gmail.com
Requires-Python: >=3.10,<4.0
Classifier: Programming Language :: Python :: 3
Classifier: Programming Language :: Python :: 3.10
Classifier: Programming Language :: Python :: 3.11
Requires-Dist: feedparser (>=6.0.10,<7.0.0)
Requires-Dist: google-cloud-storage (>=2.9.0,<3.0.0)
Requires-Dist: openai (>=0.27.7,<0.28.0)
Requires-Dist: requests (>=2.30.0,<3.0.0)
Requires-Dist: tiktoken (>=0.4.0,<0.5.0)
